impostor/__init__.py
impostor/admin.py
impostor/apps.py
impostor/backend.py
impostor/forms.py
impostor/models.py
impostor/migrations/0001_initial.py
impostor/migrations/0002_auto_20200616_1336.py
impostor/migrations/__init__.py
impostor/templates/delete_nono.html
impostor/templates/admin/base_site.html
impostor/templates/admin/impostor/impostorlog/change_form.html
impostor/templates/admin/impostor/impostorlog/change_list.html
impostor/templatetags/__init__.py
impostor/templatetags/impostor_tags.py
impostor-3.2.0.dist-info/licenses/AUTHORS
impostor-3.2.0.dist-info/licenses/LICENSE
impostor-3.2.0.dist-info/METADATA
impostor-3.2.0.dist-info/WHEEL
impostor-3.2.0.dist-info/top_level.txt
impostor-3.2.0.dist-info/RECORD
